pgbm-2.3.0.dist-info/RECORD
pgbm-2.3.0.dist-info/LICENSE
pgbm-2.3.0.dist-info/WHEEL
pgbm-2.3.0.dist-info/NOTICE
pgbm-2.3.0.dist-info/top_level.txt
pgbm-2.3.0.dist-info/METADATA
pgbm/__init__.py
pgbm/torch/splitgain_cuda.cpp
pgbm/torch/splitgain_kernel.cu
pgbm/torch/__init__.py
pgbm/torch/pgbm.py
pgbm/torch/splitgain_cpu.cpp
pgbm/torch/pgbm_dist.py
pgbm/torch/tests/test_estimator.py
pgbm/torch/tests/__init__.py
pgbm/.dylibs/libomp.dylib
pgbm/sklearn/predictor.py
pgbm/sklearn/binning.py
pgbm/sklearn/_binning.cpython-39-darwin.so
pgbm/sklearn/_bitset.pyx
pgbm/sklearn/common.c
pgbm/sklearn/histogram.c
pgbm/sklearn/_predictor.pyx
pgbm/sklearn/splitting.pyx
pgbm/sklearn/histogram.pyx
pgbm/sklearn/_bitset.cpython-39-darwin.so
pgbm/sklearn/gradient_boosting.py
pgbm/sklearn/splitting.cpython-39-darwin.so
pgbm/sklearn/common.cpython-39-darwin.so
pgbm/sklearn/__init__.py
pgbm/sklearn/_gradient_boosting.cpython-39-darwin.so
pgbm/sklearn/_predictor.c
pgbm/sklearn/distributions.py
pgbm/sklearn/utils.c
pgbm/sklearn/_gradient_boosting.pyx
pgbm/sklearn/grower.py
pgbm/sklearn/histogram.cpython-39-darwin.so
pgbm/sklearn/_binning.pyx
pgbm/sklearn/_predictor.cpython-39-darwin.so
pgbm/sklearn/_gradient_boosting.c
pgbm/sklearn/utils.cpython-39-darwin.so
pgbm/sklearn/splitting.c
pgbm/sklearn/_bitset.c
pgbm/sklearn/common.pyx
pgbm/sklearn/utils.pyx
pgbm/sklearn/_binning.c
pgbm/sklearn/tests/test_monotonic_contraints.py
pgbm/sklearn/tests/test_grower.py
pgbm/sklearn/tests/test_bitset.py
pgbm/sklearn/tests/test_binning.py
pgbm/sklearn/tests/test_estimator.py
pgbm/sklearn/tests/__init__.py
pgbm/sklearn/tests/test_splitting.py
pgbm/sklearn/tests/test_predictor.py
pgbm/sklearn/tests/test_gradient_boosting.py
pgbm/sklearn/tests/test_warm_start.py
pgbm/sklearn/tests/test_compare_lightgbm.py
pgbm/sklearn/tests/test_histogram.py
