Metadata-Version: 2.1
Name: pgbm
Version: 2.3.0
Summary: Probabilistic Gradient Boosting Machines
Home-page: https://github.com/elephaint/pgbm
Author: Olivier Sprangers
Author-email: o.r.sprangers@uva.nl
Classifier: Programming Language :: Python :: 3.8
Classifier: License :: OSI Approved :: Apache Software License
Classifier: Operating System :: OS Independent
Requires-Python: >=3.8,<3.12
License-File: LICENSE
License-File: NOTICE
Requires-Dist: scikit-learn >=1.2.0
Requires-Dist: ninja >=1.10.2.2
Requires-Dist: numba >=0.56
